DualRegev/Config.py
DualRegev/__init__.py
DualRegev/Cipher/Crypto.py
DualRegev/Cipher/__init__.py
DualRegev/IO/Converter.py
DualRegev/IO/Error.py
DualRegev/IO/String.py
DualRegev/IO/__init__.py
DualRegev/Math/Matrix.py
DualRegev/Math/Prime.py
DualRegev/Math/__init__.py
DualRegevEncryption-1.0.0.dist-info/LICENSE.txt
DualRegevEncryption-1.0.0.dist-info/METADATA
DualRegevEncryption-1.0.0.dist-info/WHEEL
DualRegevEncryption-1.0.0.dist-info/top_level.txt
DualRegevEncryption-1.0.0.dist-info/RECORD
