Metadata-Version: 2.1
Name: DualRegevEncryption
Version: 1.0.0
Summary: Dual Regev Encryption
Author-email: ShiXun <tomcruise890604@gmail.com>
Project-URL: Homepage, https://github.com/ShiXun0604/DualRegevEncryption
Project-URL: Issues, https://github.com/ShiXun0604/DualRegevEncryption/issues
Classifier: Programming Language :: Python :: 3
Classifier: License :: OSI Approved :: MIT License
Classifier: Operating System :: OS Independent
Requires-Python: >=3.9
License-File: LICENSE.txt
